senor_octopus/__init__.py
senor_octopus/cli.py
senor_octopus/exceptions.py
senor_octopus/graph.py
senor_octopus/lib.py
senor_octopus/scheduler.py
senor_octopus/types.py
senor_octopus/filters/__init__.py
senor_octopus/filters/deserialize.py
senor_octopus/filters/format.py
senor_octopus/filters/jinja.py
senor_octopus/filters/jpath.py
senor_octopus/filters/serialize.py
senor_octopus/sinks/__init__.py
senor_octopus/sinks/log.py
senor_octopus/sinks/mqtt.py
senor_octopus/sinks/pushover.py
senor_octopus/sinks/slack.py
senor_octopus/sinks/sms.py
senor_octopus/sinks/tuya.py
senor_octopus/sinks/db/postgresql.py
senor_octopus/sources/__init__.py
senor_octopus/sources/awair.py
senor_octopus/sources/crypto.py
senor_octopus/sources/mqtt.py
senor_octopus/sources/rand.py
senor_octopus/sources/speed.py
senor_octopus/sources/sqla.py
senor_octopus/sources/static.py
senor_octopus/sources/stock.py
senor_octopus/sources/sun.py
senor_octopus/sources/weatherapi.py
senor_octopus/sources/whistle.py
senor_octopus/sources/udp/__init__.py
senor_octopus/sources/udp/main.py
senor_octopus/sources/udp/protocols/__init__.py
senor_octopus/sources/udp/protocols/micron_bolt_mini_2.py
senor_octopus-0.2.0.dist-info/AUTHORS.rst
senor_octopus-0.2.0.dist-info/LICENSE.txt
senor_octopus-0.2.0.dist-info/METADATA
senor_octopus-0.2.0.dist-info/WHEEL
senor_octopus-0.2.0.dist-info/entry_points.txt
senor_octopus-0.2.0.dist-info/top_level.txt
senor_octopus-0.2.0.dist-info/RECORD
