Metadata-Version: 2.1
Name: senor-octopus
Version: 0.2.0
Summary: A streaming hub. Sort of.
Home-page: https://github.com/betodealmeida/senor-octopus
Author: Beto Dealmeida
Author-email: roberto@dealmeida.net
License: MIT
Platform: any
Classifier: Development Status :: 4 - Beta
Classifier: Programming Language :: Python :: 3.8
Classifier: Programming Language :: Python :: 3.9
Classifier: Programming Language :: Python :: 3.10
Classifier: Programming Language :: Python :: 3.11
Requires-Python: >=3.8
License-File: LICENSE.txt
License-File: AUTHORS.rst
Requires-Dist: PyYAML (>=5.4)
Requires-Dist: asciidag (>=0.2.0)
Requires-Dist: asyncstdlib (>=3.9.1)
Requires-Dist: crontab (>=0.22.9)
Requires-Dist: durations (>=0.3.3)
Requires-Dist: typing-extensions (>=3.7.4.3)
Requires-Dist: importlib-metadata ; python_version < "3.8"
Provides-Extra: filter.jinja
Requires-Dist: jinja2 (>=2.11.3) ; extra == 'filter.jinja'
Provides-Extra: filter.jsonpath
Requires-Dist: jsonpath-python (>=1.0.5) ; extra == 'filter.jsonpath'
Provides-Extra: sink.db.postgres
Requires-Dist: aiopg (>=1.1.0) ; extra == 'sink.db.postgres'
Requires-Dist: psycopg2-binary (>=2.8.6) ; extra == 'sink.db.postgres'
Provides-Extra: sink.mqtt
Requires-Dist: asyncio-mqtt (>=0.8.1) ; extra == 'sink.mqtt'
Provides-Extra: sink.pushover
Requires-Dist: httpx (>=0.17.1) ; extra == 'sink.pushover'
Provides-Extra: sink.slack
Requires-Dist: slack-sdk (>=3.7.0) ; extra == 'sink.slack'
Provides-Extra: sink.sms
Requires-Dist: twilio (>=6.58.0) ; extra == 'sink.sms'
Provides-Extra: sink.tuya
Requires-Dist: tuyapy (>=0.1.4) ; extra == 'sink.tuya'
Requires-Dist: typing-extensions (>=3.7.4.3) ; extra == 'sink.tuya'
Provides-Extra: source.awair
Requires-Dist: python-dateutil (>=2.8.1) ; extra == 'source.awair'
Requires-Dist: httpx (>=0.17.1) ; extra == 'source.awair'
Provides-Extra: source.crypto
Requires-Dist: cryptocompare (>=0.7.5) ; extra == 'source.crypto'
Provides-Extra: source.mqtt
Requires-Dist: asyncio-mqtt (>=0.8.1) ; extra == 'source.mqtt'
Requires-Dist: paho-mqtt (>=1.5.1) ; extra == 'source.mqtt'
Provides-Extra: source.speedtest
Requires-Dist: speedtest-cli (>=2.1.3) ; extra == 'source.speedtest'
Provides-Extra: source.sqla
Requires-Dist: sqlalchemy (>=1.4.3) ; extra == 'source.sqla'
Provides-Extra: source.stock
Requires-Dist: beautifulsoup4 (>=4.9.3) ; extra == 'source.stock'
Requires-Dist: stockquotes (>=2.0.1) ; extra == 'source.stock'
Provides-Extra: source.sun
Requires-Dist: suntime (>=1.2.5) ; extra == 'source.sun'
Provides-Extra: source.weatherapi
Requires-Dist: httpx (>=0.17.1) ; extra == 'source.weatherapi'
Provides-Extra: source.whistle
Requires-Dist: aiohttp (>=3.7.4.post0) ; extra == 'source.whistle'
Requires-Dist: python-geohash (>=0.8.5) ; extra == 'source.whistle'
Requires-Dist: pywhistle (>=0.0.2) ; extra == 'source.whistle'
Provides-Extra: testing
Requires-Dist: aioresponses (>=0.7.2) ; extra == 'testing'
Requires-Dist: aiotools (>=1.2.1) ; extra == 'testing'
Requires-Dist: codespell (>=2.1.0) ; extra == 'testing'
Requires-Dist: freezegun (>=1.1.0) ; extra == 'testing'
Requires-Dist: pip-tools (>=6.4.0) ; extra == 'testing'
Requires-Dist: pre-commit (>=2.13.0) ; extra == 'testing'
Requires-Dist: pylint (>=2.17.2) ; extra == 'testing'
Requires-Dist: pytest (>=6.2.4) ; extra == 'testing'
Requires-Dist: pytest-asyncio (>=0.14.0) ; extra == 'testing'
Requires-Dist: pytest-cov (>=2.11.1) ; extra == 'testing'
Requires-Dist: pytest-httpx (>=0.11.0) ; extra == 'testing'
Requires-Dist: pytest-mock (>=3.5.1) ; extra == 'testing'
Requires-Dist: requests-mock (>=1.10.0) ; extra == 'testing'
Requires-Dist: setuptools (>=57.0.0) ; extra == 'testing'
